arcana/bids/__init__.py
arcana/bids/_version.py
arcana/bids/cli.py
arcana/bids/data.py
arcana/bids/deploy.py
arcana/bids/tasks.py
arcana/bids/tests/test_cli.py
arcana/bids/tests/test_data.py
arcana/bids/tests/test_tasks.py
arcana_bids-0.2.7.dist-info/METADATA
arcana_bids-0.2.7.dist-info/WHEEL
arcana_bids-0.2.7.dist-info/licenses/LICENSE
arcana_bids-0.2.7.dist-info/RECORD
