Metadata-Version: 2.3
Name: arcana-bids
Version: 0.2.7
Summary: An Arcana extension for interacting with Brain Imaging Structure (BIDS) datasets and associated "Apps"
Project-URL: documentation, https://arcana.readthedocs.io
Project-URL: repository, https://github.com/ArcanaFramework/arcana-bids.git
Author-email: "Thomas G. Close" <tom.g.close@gmail.com>
Maintainer-email: "Thomas G. Close" <tom.g.close@gmail.com>
License: Creative Commons Attribution 4.0 International Public License
License-File: LICENSE
Keywords: arcana
Classifier: Development Status :: 3 - Alpha
Classifier: Environment :: Console
Classifier: Intended Audience :: Science/Research
Classifier: License :: OSI Approved :: Apache Software License
Classifier: Operating System :: MacOS :: MacOS X
Classifier: Operating System :: POSIX :: Linux
Classifier: Programming Language :: Python :: 3.8
Classifier: Programming Language :: Python :: 3.9
Classifier: Programming Language :: Python :: 3.10
Classifier: Programming Language :: Python :: 3.11
Classifier: Topic :: Scientific/Engineering
Requires-Python: >=3.8
Requires-Dist: arcana
Requires-Dist: fileformats-medimage[extended]>=0.2.1
Requires-Dist: fileformats[extended]>=0.3.3
Requires-Dist: jq>=1.4.0
Provides-Extra: dev
Requires-Dist: black; extra == 'dev'
Requires-Dist: codespell; extra == 'dev'
Requires-Dist: flake8; extra == 'dev'
Requires-Dist: flake8-pyproject; extra == 'dev'
Requires-Dist: pre-commit; extra == 'dev'
Provides-Extra: doc
Requires-Dist: docutils>=0.10; extra == 'doc'
Requires-Dist: furo>=2022.2.14.1; extra == 'doc'
Requires-Dist: mock>1.0; extra == 'doc'
Requires-Dist: numpydoc>=0.6.0; extra == 'doc'
Requires-Dist: packaging; extra == 'doc'
Requires-Dist: sphinx-argparse>=0.2.0; extra == 'doc'
Requires-Dist: sphinx-click>=3.1; extra == 'doc'
Requires-Dist: sphinx>=2.1.2; extra == 'doc'
Provides-Extra: test
Requires-Dist: fileformats-testing; extra == 'test'
Requires-Dist: medimages4tests>=0.3; extra == 'test'
Requires-Dist: pytest-cov>=2.12.1; extra == 'test'
Requires-Dist: pytest-env>=0.6.2; extra == 'test'
Requires-Dist: pytest>=5.4.3; extra == 'test'
